wbg/msd/__init__.py
wbg/msd/_protocols.py
wbg/msd/app.py
wbg/msd/db.py
wbg/msd/entity.py
wbg/msd/env.py
wbg/msd/link.py
wbg/msd/py.typed
wbg_msd-1.0.0.dist-info/METADATA
wbg_msd-1.0.0.dist-info/WHEEL
wbg_msd-1.0.0.dist-info/top_level.txt
wbg_msd-1.0.0.dist-info/RECORD
